[
  {
    "standId": 9,
    "id": 1,
    "type": "standClosed"
  },
  {
    "standId": 6,
    "id": 2,
    "type": "standClosed"
  },
  {
    "standId": 12,
    "start": 1108,
    "end": 1420,
    "id": 3,
    "type": "standTemporarilyClosed"
  },
  {
    "standId": 3,
    "start": 1029,
    "end": 1360,
    "condition": {
      "categories": [
        1
      ],
      "type": "category"
    },
    "id": 4,
    "type": "standConditionallyClosed"
  },
  {
    "standId": 10,
    "start": 68,
    "end": 506,
    "condition": {
      "weight": 70.0,
      "type": "weight"
    },
    "id": 5,
    "type": "standConditionallyClosed"
  },
  {
    "standId": 11,
    "start": 240,
    "end": 1035,
    "condition": {
      "engineTypes": [
        1
      ],
      "type": "engineType"
    },
    "id": 6,
    "type": "standConditionallyClosed"
  },
  {
    "standId": 14,
    "id": 7,
    "type": "standClosed"
  },
  {
    "flightId": 2,
    "delay": 255,
    "id": 8,
    "type": "flightDelayed"
  },
  {
    "flightId": 24,
    "delay": 34,
    "id": 9,
    "type": "flightDelayed"
  },
  {
    "flightId": 1,
    "delay": 216,
    "id": 10,
    "type": "flightDelayed"
  },
  {
    "flightId": 68,
    "delay": 36,
    "id": 11,
    "type": "flightDelayed"
  },
  {
    "flight": {
      "id": 94,
      "scheduled": "20:25",
      "actual": "20:25",
      "turnaroundTime": 33,
      "gateId": 8,
      "standId": 5,
      "code": "345",
      "noOfPassengers": 108,
      "transfersIds": [],
      "aircraftId": 24,
      "priority": 2,
      "categoryId": 1,
      "destination": "Brussels"
    },
    "id": 12,
    "type": "flightAdded"
  },
  {
    "flight": {
      "id": 95,
      "scheduled": "17:26",
      "actual": "17:26",
      "turnaroundTime": 48,
      "gateId": 3,
      "standId": 8,
      "code": "338",
      "noOfPassengers": 90,
      "transfersIds": [],
      "aircraftId": 18,
      "priority": 1,
      "categoryId": 1,
      "destination": "Amsterdam"
    },
    "id": 13,
    "type": "flightAdded"
  },
  {
    "flightId": 56,
    "delay": 218,
    "id": 14,
    "type": "flightDelayed"
  },
  {
    "flight": {
      "id": 96,
      "scheduled": "18:53",
      "actual": "18:53",
      "turnaroundTime": 43,
      "gateId": 22,
      "standId": 10,
      "code": "104",
      "noOfPassengers": 101,
      "transfersIds": [],
      "aircraftId": 24,
      "priority": 1,
      "categoryId": 1,
      "destination": "Copenhagen"
    },
    "id": 15,
    "type": "flightAdded"
  },
  {
    "flight": {
      "id": 97,
      "scheduled": "16:44",
      "actual": "16:44",
      "turnaroundTime": 49,
      "gateId": 23,
      "standId": 11,
      "code": "347",
      "noOfPassengers": 112,
      "transfersIds": [],
      "aircraftId": 1,
      "priority": 2,
      "categoryId": 1,
      "destination": "Warszaw"
    },
    "id": 16,
    "type": "flightAdded"
  },
  {
    "flight": {
      "id": 98,
      "scheduled": "17:19",
      "actual": "17:19",
      "turnaroundTime": 40,
      "gateId": 10,
      "standId": 6,
      "code": "238",
      "noOfPassengers": 90,
      "transfersIds": [],
      "aircraftId": 21,
      "priority": 1,
      "categoryId": 1,
      "destination": "Katowice"
    },
    "id": 17,
    "type": "flightAdded"
  },
  {
    "flight": {
      "id": 99,
      "scheduled": "07:38",
      "actual": "07:38",
      "turnaroundTime": 40,
      "gateId": 13,
      "standId": 8,
      "code": "812",
      "noOfPassengers": 87,
      "transfersIds": [],
      "aircraftId": 9,
      "priority": 1,
      "categoryId": 1,
      "destination": "Budapest"
    },
    "id": 18,
    "type": "flightAdded"
  },
  {
    "flightId": 49,
    "delay": 118,
    "id": 19,
    "type": "flightDelayed"
  },
  {
    "flightId": 28,
    "delay": 51,
    "id": 20,
    "type": "flightDelayed"
  },
  {
    "flight": {
      "id": 100,
      "scheduled": "11:43",
      "actual": "11:43",
      "turnaroundTime": 34,
      "gateId": 2,
      "standId": 2,
      "code": "812",
      "noOfPassengers": 95,
      "transfersIds": [],
      "aircraftId": 10,
      "priority": 1,
      "categoryId": 1,
      "destination": "Berlin"
    },
    "id": 21,
    "type": "flightAdded"
  },
  {
    "flightId": 27,
    "delay": 63,
    "id": 22,
    "type": "flightDelayed"
  },
  {
    "flight": {
      "id": 101,
      "scheduled": "03:56",
      "actual": "03:56",
      "turnaroundTime": 43,
      "gateId": 19,
      "standId": 6,
      "code": "775",
      "noOfPassengers": 102,
      "transfersIds": [],
      "aircraftId": 21,
      "priority": 1,
      "categoryId": 1,
      "destination": "Katowice"
    },
    "id": 23,
    "type": "flightAdded"
  },
  {
    "flight": {
      "id": 102,
      "scheduled": "20:46",
      "actual": "20:46",
      "turnaroundTime": 38,
      "gateId": 22,
      "standId": 10,
      "code": "149",
      "noOfPassengers": 80,
      "transfersIds": [],
      "aircraftId": 24,
      "priority": 2,
      "categoryId": 1,
      "destination": "Dusseldorf"
    },
    "id": 24,
    "type": "flightAdded"
  }
]