[
  {
    "standId": 6,
    "start": 926,
    "end": 1014,
    "id": 1,
    "type": "standTemporarilyClosed"
  },
  {
    "standId": 1,
    "start": 1156,
    "end": 1189,
    "condition": {
      "categories": [
        1
      ],
      "type": "category"
    },
    "id": 2,
    "type": "standConditionallyClosed"
  },
  {
    "standId": 14,
    "start": 183,
    "end": 617,
    "id": 3,
    "type": "standTemporarilyClosed"
  },
  {
    "standId": 12,
    "id": 4,
    "type": "standClosed"
  },
  {
    "flight": {
      "id": 94,
      "scheduled": "07:15",
      "actual": "07:15",
      "turnaroundTime": 33,
      "gateId": 22,
      "standId": 10,
      "code": "783",
      "noOfPassengers": 85,
      "transfersIds": [],
      "aircraftId": 8,
      "priority": 1,
      "categoryId": 1,
      "destination": "Copenhagen"
    },
    "id": 5,
    "type": "flightAdded"
  },
  {
    "flightId": 54,
    "delay": 138,
    "id": 6,
    "type": "flightDelayed"
  },
  {
    "flightId": 92,
    "delay": 163,
    "id": 7,
    "type": "flightDelayed"
  },
  {
    "flightId": 67,
    "delay": 270,
    "id": 8,
    "type": "flightDelayed"
  }
]